the_guardian
