Metadata-Version: 1.1
Name: the-guardian
Version: 0.5
Summary: A python guardian which will take care that you don't waste time.
Home-page: https://github.com/amanabt/the-guardian
Author: Aman Abhishek Tiwari
Author-email: aman.iitk072@gmail.com
License: UNKNOWN
Keywords: utilities
Platform: UNKNOWN
Classifier: Development Status :: 3 - Alpha
Classifier: Intended Audience :: End Users/Desktop
Classifier: Topic :: Utilities
Classifier: Programming Language :: Python :: 3.5
Classifier: Operating System :: OS Independent
Classifier: Natural Language :: English
Classifier: Environment :: Console
